setup.py
odprep/__init__.py
odprep.egg-info/PKG-INFO
odprep.egg-info/SOURCES.txt
odprep.egg-info/dependency_links.txt
odprep.egg-info/not-zip-safe
odprep.egg-info/requires.txt
odprep.egg-info/top_level.txt